Workbook

Sheet Leia-me
A1: Planilha de Precificação — Caramelo Pet
A3: COMO USAR
A4: 1. Na aba 'Taxas', confira as comissões do Mercado Livre e da Shopee (células amarelas).
A5: Os valores já preenchidos são os típicos de 2026, mas as plataformas mudam as taxas —
A6: confira os valores oficiais no Seller Center do Mercado Livre e no Seller Centre da Shopee.
A7: 2. Na aba 'Precificação', preencha as células amarelas de cada produto:
A8: nome, custo de compra (o que você pagou na 25 de Março / Brás), embalagem e a margem de lucro desejada.
A9: 3. A planilha calcula sozinha o preço de venda sugerido em cada canal (site, Mercado Livre e Shopee)
A10: e o lucro que sobra em cada venda.
A12: LEGENDA
A13: Células amarelas com texto azul = você preenche.
A14: Células brancas com texto preto = fórmulas, não mexa.
... A20: No site próprio não há comissão, por isso o preço pode ser menor (ou o lucro maior).

Sheet Taxas
A1: Taxas dos canais de venda
A3: Canal / taxa | B3: Valor | C3: Observação
A4: Mercado Livre — comissão (anúncio Clássico) | B4: 0.13 | C4: Varia de 10% a 14% conforme a categoria. Confira no Seller Center.
A5: Mercado Livre — tarifa fixa (produto abaixo de R$ 79) | B5: 6.5 | C5: Tarifa variável por peso/faixa de preço; acima de R$ 79 não há tarifa fixa.
A6: Shopee — comissão | B6: 0.2 | C6: 14% a 20% conforme a faixa de preço (20% para itens até R$ 79,99).
A7: Shopee — taxa fixa por item | B7: 4 | C7: R$ 4 a R$ 26 conforme o valor; vendedor CPF paga R$ 7 até atingir volume.
A8: Margem de lucro padrão (usada se o produto não tiver margem própria) | B8: 0.3 | C8: 30% de margem sobre o preço de venda é um bom ponto de partida.
A10: Fonte dos valores padrão: tabelas públicas de taxas do Mercado Livre e da Shopee (Brasil, 2026), informadas pelo usuário/pesquisa em set/2026. Sempre confirme nos canais oficiais antes de precificar.

Sheet Precificação
A1: Precificação por canal
A2: Preencha as colunas amarelas (A a D). Os preços sugeridos garantem a margem desejada já descontando comissões e taxas fixas de cada canal.
A4: Produto | B4: Custo de compra | C4: Embalagem/extras | D4: Margem desejada | E4: Custo total | F4: Preço site próprio | G4: Lucro no site | H4: Preço Mercado Livre | I4: Lucro no ML | J4: Preço Shopee | K4: Lucro na Shopee
A5: Coleira ajustável com fivela | B5: 7 | C5: 1.5 | E5: =IF($A5="","",B5+C5) -> 8.5 | F5: =IF($A5="","",IFERROR(E5/(1-IF(D5="",Taxas!$B$8,D5)),"margem inválida")) -> 12.142857 | G5: =IF($A5="","",F5-E5) -> 3.6428571 | H5: =IF($A5="","",IFERROR(IF(E5/(1-IF(D5="",Taxas!$B$8,D5)-Taxas!$B$4)>=79,E5/(1-IF(D5="",Taxas!$B$8,D5)-Taxas!$B$4),(E5+Taxas!$B$5)/(1-IF(D5="",Taxas!$B$8,D5)-Taxas!$B$4)),"margem+comissão ≥ 100%")) -> 26.315789 | I5: =IF($A5="","",IF(ISNUMBER(H5),H5*(1-Taxas!$B$4)-E5-IF(H5<79,Taxas!$B$5,0),"")) -> 7.8947368 | J5: =IF($A5="","",IFERROR((E5+Taxas!$B$7)/(1-IF(D5="",Taxas!$B$8,D5)-Taxas!$B$6),"margem+comissão ≥ 100%")) -> 25 | K5: =IF($A5="","",IF(ISNUMBER(J5),J5*(1-Taxas!$B$6)-E5-Taxas!$B$7,"")) -> 7.5
A6: Guia retrátil 5 metros | B6: 18 | C6: 2 | E6: =IF($A6="","",B6+C6) -> 20 | F6: =IF($A6="","",IFERROR(E6/(1-IF(D6="",Taxas!$B$8,D6)),"margem inválida")) -> 28.571429 | G6: =IF($A6="","",F6-E6) -> 8.5714286 | H6: =IF($A6="","",IFERROR(IF(E6/(1-IF(D6="",Taxas!$B$8,D6)-Taxas!$B$4)>=79,E6/(1-IF(D6="",Taxas!$B$8,D6)-Taxas!$B$4),(E6+Taxas!$B$5)/(1-IF(D6="",Taxas!$B$8,D6)-Taxas!$B$4)),"margem+comissão ≥ 100%")) -> 46.491228 | I6: =IF($A6="","",IF(ISNUMBER(H6),H6*(1-Taxas!$B$4)-E6-IF(H6<79,Taxas!$B$5,0),"")) -> 13.947368 | J6: =IF($A6="","",IFERROR((E6+Taxas!$B$7)/(1-IF(D6="",Taxas!$B$8,D6)-Taxas!$B$6),"margem+comissão ≥ 100%")) -> 48 | K6: =IF($A6="","",IF(ISNUMBER(J6),J6*(1-Taxas!$B$6)-E6-Taxas!$B$7,"")) -> 14.4
A7: Peitoral acolchoado | B7: 14 | C7: 1.5 | E7: =IF($A7="","",B7+C7) -> 15.5 | F7: =IF($A7="","",IFERROR(E7/(1-IF(D7="",Taxas!$B$8,D7)),"margem inválida")) -> 22.142857 | G7: =IF($A7="","",F7-E7) -> 6.6428571 | H7: =IF($A7="","",IFERROR(IF(E7/(1-IF(D7="",Taxas!$B$8,D7)-Taxas!$B$4)>=79,E7/(1-IF(D7="",Taxas!$B$8,D7)-Taxas!$B$4),(E7+Taxas!$B$5)/(1-IF(D7="",Taxas!$B$8,D7)-Taxas!$B$4)),"margem+comissão ≥ 100%")) -> 38.596491 | I7: =IF($A7="","",IF(ISNUMBER(H7),H7*(1-Taxas!$B$4)-E7-IF(H7<79,Taxas!$B$5,0),"")) -> 11.578947 | J7: =IF($A7="","",IFERROR((E7+Taxas!$B$7)/(1-IF(D7="",Taxas!$B$8,D7)-Taxas!$B$6),"margem+comissão ≥ 100%")) -> 39 | K7: =IF($A7="","",IF(ISNUMBER(J7),J7*(1-Taxas!$B$6)-E7-Taxas!$B$7,"")) -> 11.7
A8: Mordedor de borracha maciça | B8: 5 | C8: 1 | E8: =IF($A8="","",B8+C8) -> 6 | F8: =IF($A8="","",IFERROR(E8/(1-IF(D8="",Taxas!$B$8,D8)),"margem inválida")) -> 8.5714286 | G8: =IF($A8="","",F8-E8) -> 2.5714286 | H8: =IF($A8="","",IFERROR(IF(E8/(1-IF(D8="",Taxas!$B$8,D8)-Taxas!$B$4)>=79,E8/(1-IF(D8="",Taxas!$B$8,D8)-Taxas!$B$4),(E8+Taxas!$B$5)/(1-IF(D8="",Taxas!$B$8,D8)-Taxas!$B$4)),"margem+comissão ≥ 100%")) -> 21.929825 | I8: =IF($A8="","",IF(ISNUMBER(H8),H8*(1-Taxas!$B$4)-E8-IF(H8<79,Taxas!$B$5,0),"")) -> 6.5789474 | J8: =IF($A8="","",IFERROR((E8+Taxas!$B$7)/(1-IF(D8="",Taxas!$B$8,D8)-Taxas!$B$6),"margem+comissão ≥ 100%")) -> 20 | K8: =IF($A8="","",IF(ISNUMBER(J8),J8*(1-Taxas!$B$6)-E8-Taxas!$B$7,"")) -> 6
A9: Bolinha com apito | B9: 2.5 | C9: 1 | E9: =IF($A9="","",B9+C9) -> 3.5 | F9: =IF($A9="","",IFERROR(E9/(1-IF(D9="",Taxas!$B$8,D9)),"margem inválida")) -> 5 | G9: =IF($A9="","",F9-E9) -> 1.5 | H9: =IF($A9="","",IFERROR(IF(E9/(1-IF(D9="",Taxas!$B$8,D9)-Taxas!$B$4)>=79,E9/(1-IF(D9="",Taxas!$B$8,D9)-Taxas!$B$4),(E9+Taxas!$B$5)/(1-IF(D9="",Taxas!$B$8,D9)-Taxas!$B$4)),"margem+comissão ≥ 100%")) -> 17.54386 | I9: =IF($A9="","",IF(ISNUMBER(H9),H9*(1-Taxas!$B$4)-E9-IF(H9<79,Taxas!$B$5,0),"")) -> 5.2631579 | J9: =IF($A9="","",IFERROR((E9+Taxas!$B$7)/(1-IF(D9="",Taxas!$B$8,D9)-Taxas!$B$6),"margem+comissão ≥ 100%")) -> 15 | K9: =IF($A9="","",IF(ISNUMBER(J9),J9*(1-Taxas!$B$6)-E9-Taxas!$B$7,"")) -> 4.5
A10: Corda dental trançada | B10: 4 | C10: 1 | E10: =IF($A10="","",B10+C10) -> 5 | F10: =IF($A10="","",IFERROR(E10/(1-IF(D10="",Taxas!$B$8,D10)),"margem inválida")) -> 7.1428571 | G10: =IF($A10="","",F10-E10) -> 2.1428571 | H10: =IF($A10="","",IFERROR(IF(E10/(1-IF(D10="",Taxas!$B$8,D10)-Taxas!$B$4)>=79,E10/(1-IF(D10="",Taxas!$B$8,D10)-Taxas!$B$4),(E10+Taxas!$B$5)/(1-IF(D10="",Taxas!$B$8,D10)-Taxas!$B$4)),"margem+comissão ≥ 100%")) -> 20.175439 | I10: =IF($A10="","",IF(ISNUMBER(H10),H10*(1-Taxas!$B$4)-E10-IF(H10<79,Taxas!$B$5,0),"")) -> 6.0526316 | J10: =IF($A10="","",IFERROR((E10+Taxas!$B$7)/(1-IF(D10="",Taxas!$B$8,D10)-Taxas!$B$6),"margem+comissão ≥ 100%")) -> 18 | K10: =IF($A10="","",IF(ISNUMBER(J10),J10*(1-Taxas!$B$6)-E10-Taxas!$B$7,"")) -> 5.4
A11: Comedouro duplo inox | B11: 12 | C11: 2.5 | E11: =IF($A11="","",B11+C11) -> 14.5 | F11: =IF($A11="","",IFERROR(E11/(1-IF(D11="",Taxas!$B$8,D11)),"margem inválida")) -> 20.714286 | G11: =IF($A11="","",F11-E11) -> 6.2142857 | H11: =IF($A11="","",IFERROR(IF(E11/(1-IF(D11="",Taxas!$B$8,D11)-Taxas!$B$4)>=79,E11/(1-IF(D11="",Taxas!$B$8,D11)-Taxas!$B$4),(E11+Taxas!$B$5)/(1-IF(D11="",Taxas!$B$8,D11)-Taxas!$B$4)),"margem+comissão ≥ 100%")) -> 36.842105 | I11: =IF($A11="","",IF(ISNUMBER(H11),H11*(1-Taxas!$B$4)-E11-IF(H11<79,Taxas!$B$5,0),"")) -> 11.052632 | J11: =IF($A11="","",IFERROR((E11+Taxas!$B$7)/(1-IF(D11="",Taxas!$B$8,D11)-Taxas!$B$6),"margem+comissão ≥ 100%")) -> 37 | K11: =IF($A11="","",IF(ISNUMBER(J11),J11*(1-Taxas!$B$6)-E11-Taxas!$B$7,"")) -> 11.1
A12: Bifinho de carne 500 g | B12: 11 | C12: 1 | E12: =IF($A12="","",B12+C12) -> 12 | F12: =IF($A12="","",IFERROR(E12/(1-IF(D12="",Taxas!$B$8,D12)),"margem inválida")) -> 17.142857 | G12: =IF($A12="","",F12-E12) -> 5.1428571 | H12: =IF($A12="","",IFERROR(IF(E12/(1-IF(D12="",Taxas!$B$8,D12)-Taxas!$B$4)>=79,E12/(1-IF(D12="",Taxas!$B$8,D12)-Taxas!$B$4),(E12+Taxas!$B$5)/(1-IF(D12="",Taxas!$B$8,D12)-Taxas!$B$4)),"margem+comissão ≥ 100%")) -> 32.45614 | I12: =IF($A12="","",IF(ISNUMBER(H12),H12*(1-Taxas!$B$4)-E12-IF(H12<79,Taxas!$B$5,0),"")) -> 9.7368421 | J12: =IF($A12="","",IFERROR((E12+Taxas!$B$7)/(1-IF(D12="",Taxas!$B$8,D12)-Taxas!$B$6),"margem+comissão ≥ 100%")) -> 32 | K12: =IF($A12="","",IF(ISNUMBER(J12),J12*(1-Taxas!$B$6)-E12-Taxas!$B$7,"")) -> 9.6
A13: Caminha redonda de pelúcia | B13: 28 | C13: 4 | E13: =IF($A13="","",B13+C13) -> 32 | F13: =IF($A13="","",IFERROR(E13/(1-IF(D13="",Taxas!$B$8,D13)),"margem inválida")) -> 45.714286 | G13: =IF($A13="","",F13-E13) -> 13.714286 | H13: =IF($A13="","",IFERROR(IF(E13/(1-IF(D13="",Taxas!$B$8,D13)-Taxas!$B$4)>=79,E13/(1-IF(D13="",Taxas!$B$8,D13)-Taxas!$B$4),(E13+Taxas!$B$5)/(1-IF(D13="",Taxas!$B$8,D13)-Taxas!$B$4)),"margem+comissão ≥ 100%")) -> 67.54386 | I13: =IF($A13="","",IF(ISNUMBER(H13),H13*(1-Taxas!$B$4)-E13-IF(H13<79,Taxas!$B$5,0),"")) -> 20.263158 | J13: =IF($A13="","",IFERROR((E13+Taxas!$B$7)/(1-IF(D13="",Taxas!$B$8,D13)-Taxas!$B$6),"margem+comissão ≥ 100%")) -> 72 | K13: =IF($A13="","",IF(ISNUMBER(J13),J13*(1-Taxas!$B$6)-E13-Taxas!$B$7,"")) -> 21.6
A14: Moletom pet com capuz | B14: 19 | C14: 2 | E14: =IF($A14="","",B14+C14) -> 21 | F14: =IF($A14="","",IFERROR(E14/(1-IF(D14="",Taxas!$B$8,D14)),"margem inválida")) -> 30 | G14: =IF($A14="","",F14-E14) -> 9 | H14: =IF($A14="","",IFERROR(IF(E14/(1-IF(D14="",Taxas!$B$8,D14)-Taxas!$B$4)>=79,E14/(1-IF(D14="",Taxas!$B$8,D14)-Taxas!$B$4),(E14+Taxas!$B$5)/(1-IF(D14="",Taxas!$B$8,D14)-Taxas!$B$4)),"margem+comissão ≥ 100%")) -> 48.245614 | I14: =IF($A14="","",IF(ISNUMBER(H14),H14*(1-Taxas!$B$4)-E14-IF(H14<79,Taxas!$B$5,0),"")) -> 14.473684 | J14: =IF($A14="","",IFERROR((E14+Taxas!$B$7)/(1-IF(D14="",Taxas!$B$8,D14)-Taxas!$B$6),"margem+comissão ≥ 100%")) -> 50 | K14: =IF($A14="","",IF(ISNUMBER(J14),J14*(1-Taxas!$B$6)-E14-Taxas!$B$7,"")) -> 15
A15: Tapete higiênico — 30 unidades | B15: 24 | C15: 3 | E15: =IF($A15="","",B15+C15) -> 27 | F15: =IF($A15="","",IFERROR(E15/(1-IF(D15="",Taxas!$B$8,D15)),"margem inválida")) -> 38.571429 | G15: =IF($A15="","",F15-E15) -> 11.571429 | H15: =IF($A15="","",IFERROR(IF(E15/(1-IF(D15="",Taxas!$B$8,D15)-Taxas!$B$4)>=79,E15/(1-IF(D15="",Taxas!$B$8,D15)-Taxas!$B$4),(E15+Taxas!$B$5)/(1-IF(D15="",Taxas!$B$8,D15)-Taxas!$B$4)),"margem+comissão ≥ 100%")) -> 58.77193 | I15: =IF($A15="","",IF(ISNUMBER(H15),H15*(1-Taxas!$B$4)-E15-IF(H15<79,Taxas!$B$5,0),"")) -> 17.631579 | J15: =IF($A15="","",IFERROR((E15+Taxas!$B$7)/(1-IF(D15="",Taxas!$B$8,D15)-Taxas!$B$6),"margem+comissão ≥ 100%")) -> 62 | K15: =IF($A15="","",IF(ISNUMBER(J15),J15*(1-Taxas!$B$6)-E15-Taxas!$B$7,"")) -> 18.6
A16: Shampoo neutro 500 ml | B16: 9 | C16: 1.5 | E16: =IF($A16="","",B16+C16) -> 10.5 | F16: =IF($A16="","",IFERROR(E16/(1-IF(D16="",Taxas!$B$8,D16)),"margem inválida")) -> 15 | G16: =IF($A16="","",F16-E16) -> 4.5 | H16: =IF($A16="","",IFERROR(IF(E16/(1-IF(D16="",Taxas!$B$8,D16)-Taxas!$B$4)>=79,E16/(1-IF(D16="",Taxas!$B$8,D16)-Taxas!$B$4),(E16+Taxas!$B$5)/(1-IF(D16="",Taxas!$B$8,D16)-Taxas!$B$4)),"margem+comissão ≥ 100%")) -> 29.824561 | I16: =IF($A16="","",IF(ISNUMBER(H16),H16*(1-Taxas!$B$4)-E16-IF(H16<79,Taxas!$B$5,0),"")) -> 8.9473684 | J16: =IF($A16="","",IFERROR((E16+Taxas!$B$7)/(1-IF(D16="",Taxas!$B$8,D16)-Taxas!$B$6),"margem+comissão ≥ 100%")) -> 29 | K16: =IF($A16="","",IF(ISNUMBER(J16),J16*(1-Taxas!$B$6)-E16-Taxas!$B$7,"")) -> 8.7
E17: =IF($A17="","",B17+C17) | F17: =IF($A17="","",IFERROR(E17/(1-IF(D17="",Taxas!$B$8,D17)),"margem inválida")) | G17: =IF($A17="","",F17-E17) | H17: =IF($A17="","",IFERROR(IF(E17/(1-IF(D17="",Taxas!$B$8,D17)-Taxas!$B$4)>=79,E17/(1-IF(D17="",Taxas!$B$8,D17)-Taxas!$B$4),(E17+Taxas!$B$5)/(1-IF(D17="",Taxas!$B$8,D17)-Taxas!$B$4)),"margem+comissão ≥ 100%")) | I17: =IF($A17="","",IF(ISNUMBER(H17),H17*(1-Taxas!$B$4)-E17-IF(H17<79,Taxas!$B$5,0),"")) | J17: =IF($A17="","",IFERROR((E17+Taxas!$B$7)/(1-IF(D17="",Taxas!$B$8,D17)-Taxas!$B$6),"margem+comissão ≥ 100%")) | K17: =IF($A17="","",IF(ISNUMBER(J17),J17*(1-Taxas!$B$6)-E17-Taxas!$B$7,""))
E18: =IF($A18="","",B18+C18) | F18: =IF($A18="","",IFERROR(E18/(1-IF(D18="",Taxas!$B$8,D18)),"margem inválida")) | G18: =IF($A18="","",F18-E18) | H18: =IF($A18="","",IFERROR(IF(E18/(1-IF(D18="",Taxas!$B$8,D18)-Taxas!$B$4)>=79,E18/(1-IF(D18="",Taxas!$B$8,D18)-Taxas!$B$4),(E18+Taxas!$B$5)/(1-IF(D18="",Taxas!$B$8,D18)-Taxas!$B$4)),"margem+comissão ≥ 100%")) | I18: =IF($A18="","",IF(ISNUMBER(H18),H18*(1-Taxas!$B$4)-E18-IF(H18<79,Taxas!$B$5,0),"")) | J18: =IF($A18="","",IFERROR((E18+Taxas!$B$7)/(1-IF(D18="",Taxas!$B$8,D18)-Taxas!$B$6),"margem+comissão ≥ 100%")) | K18: =IF($A18="","",IF(ISNUMBER(J18),J18*(1-Taxas!$B$6)-E18-Taxas!$B$7,""))
E19: =IF($A19="","",B19+C19) | F19: =IF($A19="","",IFERROR(E19/(1-IF(D19="",Taxas!$B$8,D19)),"margem inválida")) | G19: =IF($A19="","",F19-E19) | H19: =IF($A19="","",IFERROR(IF(E19/(1-IF(D19="",Taxas!$B$8,D19)-Taxas!$B$4)>=79,E19/(1-IF(D19="",Taxas!$B$8,D19)-Taxas!$B$4),(E19+Taxas!$B$5)/(1-IF(D19="",Taxas!$B$8,D19)-Taxas!$B$4)),"margem+comissão ≥ 100%")) | I19: =IF($A19="","",IF(ISNUMBER(H19),H19*(1-Taxas!$B$4)-E19-IF(H19<79,Taxas!$B$5,0),"")) | J19: =IF($A19="","",IFERROR((E19+Taxas!$B$7)/(1-IF(D19="",Taxas!$B$8,D19)-Taxas!$B$6),"margem+comissão ≥ 100%")) | K19: =IF($A19="","",IF(ISNUMBER(J19),J19*(1-Taxas!$B$6)-E19-Taxas!$B$7,""))
E20: =IF($A20="","",B20+C20) | F20: =IF($A20="","",IFERROR(E20/(1-IF(D20="",Taxas!$B$8,D20)),"margem inválida")) | G20: =IF($A20="","",F20-E20) | H20: =IF($A20="","",IFERROR(IF(E20/(1-IF(D20="",Taxas!$B$8,D20)-Taxas!$B$4)>=79,E20/(1-IF(D20="",Taxas!$B$8,D20)-Taxas!$B$4),(E20+Taxas!$B$5)/(1-IF(D20="",Taxas!$B$8,D20)-Taxas!$B$4)),"margem+comissão ≥ 100%")) | I20: =IF($A20="","",IF(ISNUMBER(H20),H20*(1-Taxas!$B$4)-E20-IF(H20<79,Taxas!$B$5,0),"")) | J20: =IF($A20="","",IFERROR((E20+Taxas!$B$7)/(1-IF(D20="",Taxas!$B$8,D20)-Taxas!$B$6),"margem+comissão ≥ 100%")) | K20: =IF($A20="","",IF(ISNUMBER(J20),J20*(1-Taxas!$B$6)-E20-Taxas!$B$7,""))
E21: =IF($A21="","",B21+C21) | F21: =IF($A21="","",IFERROR(E21/(1-IF(D21="",Taxas!$B$8,D21)),"margem inválida")) | G21: =IF($A21="","",F21-E21) | H21: =IF($A21="","",IFERROR(IF(E21/(1-IF(D21="",Taxas!$B$8,D21)-Taxas!$B$4)>=79,E21/(1-IF(D21="",Taxas!$B$8,D21)-Taxas!$B$4),(E21+Taxas!$B$5)/(1-IF(D21="",Taxas!$B$8,D21)-Taxas!$B$4)),"margem+comissão ≥ 100%")) | I21: =IF($A21="","",IF(ISNUMBER(H21),H21*(1-Taxas!$B$4)-E21-IF(H21<79,Taxas!$B$5,0),"")) | J21: =IF($A21="","",IFERROR((E21+Taxas!$B$7)/(1-IF(D21="",Taxas!$B$8,D21)-Taxas!$B$6),"margem+comissão ≥ 100%")) | K21: =IF($A21="","",IF(ISNUMBER(J21),J21*(1-Taxas!$B$6)-E21-Taxas!$B$7,""))
E22: =IF($A22="","",B22+C22) | F22: =IF($A22="","",IFERROR(E22/(1-IF(D22="",Taxas!$B$8,D22)),"margem inválida")) | G22: =IF($A22="","",F22-E22) | H22: =IF($A22="","",IFERROR(IF(E22/(1-IF(D22="",Taxas!$B$8,D22)-Taxas!$B$4)>=79,E22/(1-IF(D22="",Taxas!$B$8,D22)-Taxas!$B$4),(E22+Taxas!$B$5)/(1-IF(D22="",Taxas!$B$8,D22)-Taxas!$B$4)),"margem+comissão ≥ 100%")) | I22: =IF($A22="","",IF(ISNUMBER(H22),H22*(1-Taxas!$B$4)-E22-IF(H22<79,Taxas!$B$5,0),"")) | J22: =IF($A22="","",IFERROR((E22+Taxas!$B$7)/(1-IF(D22="",Taxas!$B$8,D22)-Taxas!$B$6),"margem+comissão ≥ 100%")) | K22: =IF($A22="","",IF(ISNUMBER(J22),J22*(1-Taxas!$B$6)-E22-Taxas!$B$7,""))
E23: =IF($A23="","",B23+C23) | F23: =IF($A23="","",IFERROR(E23/(1-IF(D23="",Taxas!$B$8,D23)),"margem inválida")) | G23: =IF($A23="","",F23-E23) | H23: =IF($A23="","",IFERROR(IF(E23/(1-IF(D23="",Taxas!$B$8,D23)-Taxas!$B$4)>=79,E23/(1-IF(D23="",Taxas!$B$8,D23)-Taxas!$B$4),(E23+Taxas!$B$5)/(1-IF(D23="",Taxas!$B$8,D23)-Taxas!$B$4)),"margem+comissão ≥ 100%")) | I23: =IF($A23="","",IF(ISNUMBER(H23),H23*(1-Taxas!$B$4)-E23-IF(H23<79,Taxas!$B$5,0),"")) | J23: =IF($A23="","",IFERROR((E23+Taxas!$B$7)/(1-IF(D23="",Taxas!$B$8,D23)-Taxas!$B$6),"margem+comissão ≥ 100%")) | K23: =IF($A23="","",IF(ISNUMBER(J23),J23*(1-Taxas!$B$6)-E23-Taxas!$B$7,""))
E24: =IF($A24="","",B24+C24) | F24: =IF($A24="","",IFERROR(E24/(1-IF(D24="",Taxas!$B$8,D24)),"margem inválida")) | G24: =IF($A24="","",F24-E24) | H24: =IF($A24="","",IFERROR(IF(E24/(1-IF(D24="",Taxas!$B$8,D24)-Taxas!$B$4)>=79,E24/(1-IF(D24="",Taxas!$B$8,D24)-Taxas!$B$4),(E24+Taxas!$B$5)/(1-IF(D24="",Taxas!$B$8,D24)-Taxas!$B$4)),"margem+comissão ≥ 100%")) | I24: =IF($A24="","",IF(ISNUMBER(H24),H24*(1-Taxas!$B$4)-E24-IF(H24<79,Taxas!$B$5,0),"")) | J24: =IF($A24="","",IFERROR((E24+Taxas!$B$7)/(1-IF(D24="",Taxas!$B$8,D24)-Taxas!$B$6),"margem+comissão ≥ 100%")) | K24: =IF($A24="","",IF(ISNUMBER(J24),J24*(1-Taxas!$B$6)-E24-Taxas!$B$7,""))
E25: =IF($A25="","",B25+C25) | F25: =IF($A25="","",IFERROR(E25/(1-IF(D25="",Taxas!$B$8,D25)),"margem inválida")) | G25: =IF($A25="","",F25-E25) | H25: =IF($A25="","",IFERROR(IF(E25/(1-IF(D25="",Taxas!$B$8,D25)-Taxas!$B$4)>=79,E25/(1-IF(D25="",Taxas!$B$8,D25)-Taxas!$B$4),(E25+Taxas!$B$5)/(1-IF(D25="",Taxas!$B$8,D25)-Taxas!$B$4)),"margem+comissão ≥ 100%")) | I25: =IF($A25="","",IF(ISNUMBER(H25),H25*(1-Taxas!$B$4)-E25-IF(H25<79,Taxas!$B$5,0),"")) | J25: =IF($A25="","",IFERROR((E25+Taxas!$B$7)/(1-IF(D25="",Taxas!$B$8,D25)-Taxas!$B$6),"margem+comissão ≥ 100%")) | K25: =IF($A25="","",IF(ISNUMBER(J25),J25*(1-Taxas!$B$6)-E25-Taxas!$B$7,""))
E26: =IF($A26="","",B26+C26) | F26: =IF($A26="","",IFERROR(E26/(1-IF(D26="",Taxas!$B$8,D26)),"margem inválida")) | G26: =IF($A26="","",F26-E26) | H26: =IF($A26="","",IFERROR(IF(E26/(1-IF(D26="",Taxas!$B$8,D26)-Taxas!$B$4)>=79,E26/(1-IF(D26="",Taxas!$B$8,D26)-Taxas!$B$4),(E26+Taxas!$B$5)/(1-IF(D26="",Taxas!$B$8,D26)-Taxas!$B$4)),"margem+comissão ≥ 100%")) | I26: =IF($A26="","",IF(ISNUMBER(H26),H26*(1-Taxas!$B$4)-E26-IF(H26<79,Taxas!$B$5,0),"")) | J26: =IF($A26="","",IFERROR((E26+Taxas!$B$7)/(1-IF(D26="",Taxas!$B$8,D26)-Taxas!$B$6),"margem+comissão ≥ 100%")) | K26: =IF($A26="","",IF(ISNUMBER(J26),J26*(1-Taxas!$B$6)-E26-Taxas!$B$7,""))
E27: =IF($A27="","",B27+C27) | F27: =IF($A27="","",IFERROR(E27/(1-IF(D27="",Taxas!$B$8,D27)),"margem inválida")) | G27: =IF($A27="","",F27-E27) | H27: =IF($A27="","",IFERROR(IF(E27/(1-IF(D27="",Taxas!$B$8,D27)-Taxas!$B$4)>=79,E27/(1-IF(D27="",Taxas!$B$8,D27)-Taxas!$B$4),(E27+Taxas!$B$5)/(1-IF(D27="",Taxas!$B$8,D27)-Taxas!$B$4)),"margem+comissão ≥ 100%")) | I27: =IF($A27="","",IF(ISNUMBER(H27),H27*(1-Taxas!$B$4)-E27-IF(H27<79,Taxas!$B$5,0),"")) | J27: =IF($A27="","",IFERROR((E27+Taxas!$B$7)/(1-IF(D27="",Taxas!$B$8,D27)-Taxas!$B$6),"margem+comissão ≥ 100%")) | K27: =IF($A27="","",IF(ISNUMBER(J27),J27*(1-Taxas!$B$6)-E27-Taxas!$B$7,""))
E28: =IF($A28="","",B28+C28) | F28: =IF($A28="","",IFERROR(E28/(1-IF(D28="",Taxas!$B$8,D28)),"margem inválida")) | G28: =IF($A28="","",F28-E28) | H28: =IF($A28="","",IFERROR(IF(E28/(1-IF(D28="",Taxas!$B$8,D28)-Taxas!$B$4)>=79,E28/(1-IF(D28="",Taxas!$B$8,D28)-Taxas!$B$4),(E28+Taxas!$B$5)/(1-IF(D28="",Taxas!$B$8,D28)-Taxas!$B$4)),"margem+comissão ≥ 100%")) | I28: =IF($A28="","",IF(ISNUMBER(H28),H28*(1-Taxas!$B$4)-E28-IF(H28<79,Taxas!$B$5,0),"")) | J28: =IF($A28="","",IFERROR((E28+Taxas!$B$7)/(1-IF(D28="",Taxas!$B$8,D28)-Taxas!$B$6),"margem+comissão ≥ 100%")) | K28: =IF($A28="","",IF(ISNUMBER(J28),J28*(1-Taxas!$B$6)-E28-Taxas!$B$7,""))
... E34: =IF($A34="","",B34+C34) | F34: =IF($A34="","",IFERROR(E34/(1-IF(D34="",Taxas!$B$8,D34)),"margem inválida")) | G34: =IF($A34="","",F34-E34) | H34: =IF($A34="","",IFERROR(IF(E34/(1-IF(D34="",Taxas!$B$8,D34)-Taxas!$B$4)>=79,E34/(1-IF(D34="",Taxas!$B$8,D34)-Taxas!$B$4),(E34+Taxas!$B$5)/(1-IF(D34="",Taxas!$B$8,D34)-Taxas!$B$4)),"margem+comissão ≥ 100%")) | I34: =IF($A34="","",IF(ISNUMBER(H34),H34*(1-Taxas!$B$4)-E34-IF(H34<79,Taxas!$B$5,0),"")) | J34: =IF($A34="","",IFERROR((E34+Taxas!$B$7)/(1-IF(D34="",Taxas!$B$8,D34)-Taxas!$B$6),"margem+comissão ≥ 100%")) | K34: =IF($A34="","",IF(ISNUMBER(J34),J34*(1-Taxas!$B$6)-E34-Taxas!$B$7,""))
A36: Custos de compra das linhas de exemplo são estimativas de atacado (25 de Março/Brás) só para demonstrar o cálculo — substitua pelos seus custos reais de nota.

Sheet Projeção
A1: Projeção mensal da operação
A2: Estimativa de um mês típico após 2–3 meses de operação (o 1º mês é de montagem de anúncios e reputação). Células amarelas = você ajusta; o resto calcula sozinho.
A4: Premissas | B4: Conservador | C4: Realista | D4: Otimista
A5: Anúncios por mês (Instagram/Meta) | B5: 600 | C5: 900 | D5: 1500
A6: Custo por clique — CPC | B6: 1.2 | C6: 1 | D6: 0.8
A7: Conversão do site em vendas | B7: 0.01 | C7: 0.015 | D7: 0.025
A8: Ticket médio por pedido | B8: 85 | C8: 90 | D8: 100
A9: Margem por venda (após taxas, aba Precificação) | B9: 0.3 | C9: 0.3 | D9: 0.3
A10: Pedidos por mês no Mercado Livre | B10: 20 | C10: 45 | D10: 90
A11: Pedidos por mês na Shopee | B11: 10 | C11: 30 | D11: 60
A13: Resultados | B13: Conservador | C13: Realista | D13: Otimista
A14: Visitas no site (anúncios ÷ CPC) | B14: =B5/B6 -> 500 | C14: =C5/C6 -> 900 | D14: =D5/D6 -> 1875
A15: Pedidos no site | B15: =ROUND(B14*B7,0) -> 5 | C15: =ROUND(C14*C7,0) -> 14 | D15: =ROUND(D14*D7,0) -> 47
A16: Pedidos totais (site + ML + Shopee) | B16: =B15+B10+B11 -> 35 | C16: =C15+C10+C11 -> 89 | D16: =D15+D10+D11 -> 197
A17: Faturamento do mês | B17: =B16*B8 -> 2975 | C17: =C16*C8 -> 8010 | D17: =D16*D8 -> 19700
A18: Lucro sobre os produtos | B18: =B17*B9 -> 892.5 | C18: =C17*C9 -> 2403 | D18: =D17*D9 -> 5910
A19: (−) Investimento em anúncios | B19: =-B5 -> -600 | C19: =-C5 -> -900 | D19: =-D5 -> -1500
A20: LUCRO LÍQUIDO DO MÊS | B20: =B18+B19 -> 292.5 | C20: =C18+C19 -> 1503 | D20: =D18+D19 -> 4410
A21: Lucro sobre o faturamento | B21: =IF(B17=0,0,B20/B17) -> 0.098319328 | C21: =IF(C17=0,0,C20/C17) -> 0.18764045 | D21: =IF(D17=0,0,D20/D17) -> 0.22385787
A22: Estoque girando necessário (≈45% do faturamento) | B22: =B17*0.45 -> 1338.75 | C22: =C17*0.45 -> 3604.5 | D22: =D17*0.45 -> 8865
A24: Premissas e fontes:
A25: • CPC de R$ 0,80–1,20: faixa típica de anúncios Meta (Instagram/Facebook) para varejo no Brasil; informado como estimativa, confira no seu Gerenciador de Anúncios.
A26: • Conversão de 1%–2,5%: faixa comum de e-commerce pequeno com fechamento assistido por WhatsApp; loja nova começa perto de 1%.
A27: • Pedidos de ML e Shopee: estimativa de rampa usando produtos recorrentes (tapete higiênico, areia); começam perto de zero no 1º mês.
A28: • Margem de 30%: é a margem-alvo configurada na aba Precificação (já líquida das taxas de cada canal).
A29: • Custo de mercadoria ≈ 45% do faturamento: decorre da margem de 30% + taxas médias; usado para estimar o estoque necessário.
A30: • O 1º mês tende a fechar no zero a zero ou negativo — a projeção vale para a operação já rodando.
